{
  "16823295-0": {
    "nombre": "Henry Wladimir Gonzalez Rivera",
    "correo": "hgonzalez@olitel.cl",
    "contraseña": "he6782lez//"
  },
  "8153205-2": {
    "nombre": "Rexner Alquimelec Cazangas Gallardo",
    "correo": "rcazangas@olitel.cl",
    "contraseña": "re6183gas//"
  },
  "17513251-1": {
    "nombre": "Yelem Yanin Sandoval Soto",
    "correo": "ysandoval@olitel.cl",
    "contraseña": "ye5082val//"
  },
  "16657869-8": {
    "nombre": "Patricio Andre Sudy Duran",
    "correo": "psudy@olitel.cl",
    "contraseña": "pa2751udy//"
  },
  "19061918-4": {
    "nombre": "Alfredo Alexander Arriagada Acevedo",
    "correo": "alarriagada@olitel.cl",
    "contraseña": "al3684ada//"
  },
  "10150039-k": {
    "nombre": "Cesar Enrique Valenzuela Castillo",
    "correo": "cvalenzuela@olitel.cl",
    "contraseña": "ce5138ela//"
  },
  "16923287-3": {
    "nombre": "Jonathan Mancilla Morales",
    "correo": "jomancilla@olitel.cl",
    "contraseña": "jo6439illa//"
  },
  "17348285-k": {
    "nombre": "Gerardo Andres Vargas Duran",
    "correo": "gvargas@olitel.cl",
    "contraseña": "ge5147gas//"
  },
  "9402166-9": {
    "nombre": "Erasmo Saez Jimenez",
    "correo": "esaez@olitel.cl",
    "contraseña": "er5283aez//"
  },
  "92543595-2": {
    "nombre": "Manuel Francisco Brito Cardenas",
    "correo": "mbrito@olitel.cl",
    "contraseña": "ma6483ito//"
  },
  "17315218-3": {
    "nombre": "Paola Daniela Lagos Oyaneder",
    "correo": "plagos@olitel.cl",
    "contraseña": "pa6953gos//"
  },
  "10679932-6": {
    "nombre": "Guillermo Enrique Figueroa Zamorano",
    "correo": "gfigueroa@olitel.cl",
    "contraseña": "gu6182roa//"
  },
  "8319309-3": {
    "nombre": "Marcela Ivonne Rivera Flores",
    "correo": "mrivera@olitel.cl",
    "contraseña": "ma6492era//"
  },
  "13704852-3": {
    "nombre": "Elizabeth Alejandra Rodriguez Silva",
    "correo": "erodriguez@olitel.cl",
    "contraseña": "el9182guez//"
  },
  "12880981-3": {
    "nombre": "Jessica Andrea Fredes Silva",
    "correo": "jefredes@olitel.cl",
    "contraseña": "je6492des//"
  },
  "12658005-3": {
    "nombre": "Adriano Alfonso Vasquez Miranda",
    "correo": "avasquez@olitel.cl",
    "contraseña": "adr536asv//"
  },
  "11862405-k": {
    "nombre": "Victor Hugo Cortes Seguel",
    "correo": "vcortez@olitel.cl",
    "contraseña": "vic5369cor//"
  },
  "6615834-9": {
    "nombre": "Samuel Fernando Tapia Avila",
    "correo": "stapia@olitel.cl",
    "contraseña": "sam7356Tap//"
  },
  "19443166-k": {
    "nombre": "Fernando Monroy Lincopil",
    "correo": "fmonroy@olitel.cl",
    "contraseña": "fer8462mon//"
  }
}
